mnespikes/__init__.py
mnespikes/spikes.py
mnespikes-0.1a.dist-info/LICENSE
mnespikes-0.1a.dist-info/WHEEL
mnespikes-0.1a.dist-info/METADATA
mnespikes-0.1a.dist-info/RECORD
