Metadata-Version: 1.2
Name: mnespikes
Version: 0.1a
Summary: A simple package for representing neural spike data and converting to MNE
Home-page: https://predictablynoisy.com/mne-spikes
License: UNKNOWN
Author: Chris Holdgraf
Author-email: choldgraf@berkeley.edu
Classifier: License :: OSI Approved :: MIT License
